{
  "type": "minecraft:overworld",
  "generator": {
    "type": "minecraft:noise",
    "seed": 1234,
    "biome_source": {
	  "temperature_noise": {
        "firstOctave": -7,
        "amplitudes": [
          1.0,
		  1.0
        ]
      },
	  "humidity_noise": {
        "firstOctave": -7,
        "amplitudes": [
          1.0,
		  1.0
        ]
      },
      "altitude_noise": {
        "firstOctave": -7,
        "amplitudes": [
          1.0,
          1.0
        ]
      },
      "weirdness_noise": {
        "firstOctave": -7,
        "amplitudes": [
          1.0,
          1.0
        ]
      },
      "type": "minecraft:multi_noise",
      "seed": 1234,
      "biomes": [
		{
          "biome": "minecraft:winter_alpha",
          "parameters": {
            "temperature": 0.0,
            "humidity": 0.0,
            "altitude": 0.0,
            "weirdness": 0.6,
            "offset": 0.0
          }
        },
        {
          "biome": "minecraft:winter_alpha_g",
          "parameters": {
            "temperature": 0.0,
            "humidity": 0.0,
            "altitude": 0.0,
            "weirdness": 0.8,
            "offset": 0.0
          }
        }
      ]
    },
    "settings": "minecraft:overworld"
  }
}
